RISC-V_PE/ClusterControl.v
//Cluster controller

module cluster_controller (
    input clk,                     // Clock signal
    input reset,                   // Reset signal
    //signals for instruction memory
    input [127:0] instruction_mem, // Instructions from instruction memory for each PE
    output reg [31:0] PCsIM,        // Program counter to read from instruction memory
    output reg [3:0] InstReadEn,   // Read enable signals for instruction memory 

    output reg [127:0] PCinPE,  // Program counter inputs to PEs
    output reg [127:0] instruction_outPE, // Instructions to load into PEs
    input [127:0] PCoutPE,           // Program counter outputs from PEs
    input [3:0] execution_complete,
    input last_instruction  //Input from instruction memory that last instruction was read
    );

    // Internal variables
    reg [31:0] current_pc;    // Current program counters for the last executed instruction
    reg program_start;        //Signal to initialize first instruction fetch
    reg [3:0] dependency;     //Dependency flags
    reg [127:0] instructionTemp; //Temporary instruction for loading less than 4 instructions
    reg [127:0] PCinTemp;  //Temporary PCin for loading less than 4 instructions
    reg end_execute;   //Signal to stop fetching instructions

    function [14:0] register_extraction;
        input [31:0] instruction;
        reg [6:0] opcode;            // Temporary register for opcode
        reg [4:0] rd, rs1, rs2;
        begin
            opcode = 7'b0;
            opcode = instruction[6:0]; // Extract opcode (bits [6:0])
            rd = 5'b0;
            rs1 = 5'b0;
            rs2 = 5'b0;

            case (opcode)
            7'b0110011: //Type R
            begin
                rd = instruction[11:7];
                rs1 = instruction[19:15];
                rs2 = instruction[24:20];
            end
            7'b1101111, 7'b0110111: //Types U and J
            begin
                rd = instruction[11:7];
            end
            7'b0100011, 7'b1100011: // Types S and B
            begin
                rs1 = instruction[19:15];
                rs2 = instruction[24:20];
            end
            7'b0000011, 7'b0010011: //Type I
            begin
                $display("Instruction: %b", instruction);
                rd = instruction[11:7];
                rs1 = instruction[19:15];
                $display("Rs1: %b and Rd: %b", rs1, rd);
            end
            endcase
            // Concatenate rd, rs1, rs2 into a single output
            register_extraction = {rd, rs1, rs2};
        end
    endfunction
    
    // Function definition 
    task dependency_check;
        input [127:0] instructions;
        output [3:0] dependency_flags; 
        reg [14:0] regs1, regs2, regs3, regs4; // Decoded {rd, rs1, rs2} for each instruction
        reg [4:0] rdop1, rs1op1, rs2op1; // Instruction 1: rd, rs1, rs2
        reg [4:0] rdop2, rs1op2, rs2op2; // Instruction 2: rd, rs1, rs2
        reg [4:0] rdop3, rs1op3, rs2op3; // Instruction 3: rd, rs1, rs2
        reg [4:0] rdop4, rs1op4, rs2op4; // Instruction 4: rd, rs1, rs2
        begin
            // Decode registers for all 4 instructions
            regs1 = register_extraction(instructions[31:0]);   // Instruction 1
            regs2 = register_extraction(instructions[63:32]);  // Instruction 2
            regs3 = register_extraction(instructions[95:64]);  // Instruction 3
            regs4 = register_extraction(instructions[127:96]); // Instruction 4

            // Extract rd, rs1, rs2 for each instruction
            rdop1 = regs1[14:10]; rs1op1 = regs1[9:5]; rs2op1 = regs1[4:0];
            rdop2 = regs2[14:10]; rs1op2 = regs2[9:5]; rs2op2 = regs2[4:0];
            rdop3 = regs3[14:10]; rs1op3 = regs3[9:5]; rs2op3 = regs3[4:0];
            rdop4 = regs4[14:10]; rs1op4 = regs4[9:5]; rs2op4 = regs4[4:0];

            $display("Rs1op1: %b, Rs2op1: %b, Rdop1: %b", rs1op1, rs2op1, rdop1);
            $display("Rs1op2: %b, Rs2op2: %b, Rdop2: %b", rs1op2, rs2op2, rdop2);
            $display("Rs1op3: %b, Rs2op3: %b, Rdop3: %b", rs1op3, rs2op3, rdop3);
            $display("Rs1op4: %b, Rs2op4: %b, Rdop4: %b", rs1op4, rs2op4, rdop4);

            // Reset dependency flags
            dependency_flags = 4'b0000;

            if (((rs1op2 == rdop1) || (rs2op2 == rdop1) || (rs1op2 == rs1op1) || (rs2op2 == rs1op1) || (rs1op2 == rs2op1) || (rs2op2 == rs2op1)) && (rs1op2 != 0) && (rs2op2 != 0))
            begin
                dependency_flags = dependency_flags | 4'b0010;
            end
            if (((rs1op3 == rdop1) || (rs1op3 == rdop2) || (rs2op3 == rdop1) || (rs2op3 == rdop2)|| (rs1op3 == rs1op1) || (rs1op3 == rs1op2) || (rs2op3 == rs1op1) || (rs2op3 == rs1op2) || (rs1op3 == rs2op1) || (rs1op3 == rs2op2) || (rs2op3 == rs2op1) || (rs2op3 == rs2op2)) && (rs1op3 != 0) && (rs2op3 != 0))
            begin
                dependency_flags = dependency_flags | 4'b0100;
            end
            if (((rs1op4 == rdop1) || (rs1op4 == rdop2) || (rs1op4 == rdop3) || (rs2op4 == rdop1) || (rs2op4 == rdop2) || (rs2op4 == rdop3) || (rs1op4 == rs1op1) || (rs1op4 == rs1op2)  || (rs1op4 == rs1op3) || (rs2op4 == rs1op1) || (rs2op4 == rs1op2) || (rs2op4 == rs1op3) || (rs1op4 == rs2op1) || (rs1op4 == rs2op2) || (rs1op4 == rs2op3) || (rs2op4 == rs2op1) || (rs2op4 == rs2op2) || (rs2op4 == rs2op3)) && (rs1op4 != 0) && (rs2op4 != 0))
            begin
                dependency_flags = dependency_flags | 4'b1000;
            end
        end
    endtask

    always @(posedge clk or posedge reset) begin
        if (reset) begin
            // Reset all state
            current_pc <= 32'b0;
            PCinPE <= 128'b0;
            PCsIM <= 32'b0;
            InstReadEn <= 4'b0;
            instruction_outPE <= 128'b0;
            program_start <= 1;
            dependency <= 4'b0;
            instructionTemp <= 128'b0;
            PCinTemp <= 128'b0;
            end_execute <= 0;
        end 
        else begin
            // Program counter and instruction loading assuming program has more than 4 instructions
            if (program_start)
            begin
                $display("Program started");
                PCsIM <= 32'h00000000; //Read the first instruction in the program
                InstReadEn <= 4'b1111;
                instructionTemp <= 0;
                dependency <= 0;
                if (instruction_mem != 0)
                begin
                    $display("Read instructions from memory");
                    InstReadEn <= 0;
                    dependency_check(instruction_mem, dependency);
                    $display("Dependency: %b", dependency);
                    if (dependency == 0) //There is no dependency
                    begin
                        $display("No dependency");
                        instruction_outPE = instruction_mem;
                        PCinPE = {PCsIM+32'd3, PCsIM+32'd2, PCsIM+32'd1, PCsIM};
                        current_pc = 32'd4;
                        $display("Instructions written to PEs: %h", instruction_outPE);
                        $display("Current PC: %b", current_pc);
                    end
                    else 
                    begin
                        instructionTemp[31:0] = instruction_mem[31:0];
                        PCinTemp[31:0] = PCsIM;
                        if (dependency[1] == 1'b1)
                        begin
                            $display("There is dependency on the second operation");
                            $display("Will only load instruction 0");
                            current_pc = 32'd1;
                        end 
                        else if (dependency[2] == 1'b1)
                        begin
                            $display("There is dependency on the third operation");
                            $display("Will only load instructions 0 adn 1");
                            instructionTemp[63:32] = instruction_mem[63:32];
                            PCinTemp[63:32] = PCsIM+1;
                            current_pc = 32'd2;
                        end
                        else if (dependency[3] == 1'b1)
                        begin
                            $display("There is dependency on the fourth operation");
                            $display("Will only load instructions 0, 1 and 2");
                            instructionTemp[95:64] = instruction_mem[95:64];
                            PCinTemp[95:64] = PCsIM+2;
                            current_pc = 32'd3;
                        end
                        instruction_outPE = instructionTemp;
                        PCinPE = PCinTemp;
                        $display("Instructions written to PEs: %h", instruction_outPE);
                        $display("Current PC: %b", current_pc);
                    end
                    program_start <= 0;
                end
            end
            else
            begin
                if (execution_complete != 0)
                begin
                    if (PCoutPE != PCinPE) //Means there was a break or jump
                    begin
                        if (PCoutPE[31:0] != PCinPE[31:0]) //Break comes from first operation
                        begin
                            current_pc = PCoutPE[31:0];
                        end
                        else if (PCoutPE[63:32] != PCinPE[63:32]) //Break comes from second operation
                        begin
                            current_pc = PCoutPE[63:32];
                        end
                        else if (PCoutPE[95:64] != PCinPE[95:64]) //Break comes from third operation
                        begin
                            current_pc = PCoutPE[95:64];
                        end
                        else  //Break comes from fourth operation
                        begin
                            current_pc = PCoutPE[127:96];
                        end
                    end
                    else if (!end_execute)
                    begin
                        PCsIM = current_pc;
                        InstReadEn <= 4'b1111;
                        instructionTemp <= 0;
                        dependency <= 0;
                        if (instruction_mem != 0)
                        begin
                            InstReadEn <= 0;
                            dependency_check(instruction_mem, dependency);
                            $display("Dependency: %b", dependency);
                            if (dependency == 0)
                            begin
                                $display("No dependency");
                                instruction_outPE <= instruction_mem;
                                PCinPE <= {PCsIM+32'd3, PCsIM+32'd2, PCsIM+32'd1, PCsIM};
                                current_pc <= current_pc + 4;
                            end
                            else 
                            begin
                                instructionTemp[31:0] = instruction_mem[31:0];
                                PCinTemp[31:0] = PCsIM;
                                if (dependency[1] == 1'b1)
                                begin
                                    $display("There is dependency on the second operation");
                                    $display("Will only load instruction 0");
                                    current_pc = current_pc + 1;
                                end 
                                else if (dependency[2] == 1'b1)
                                begin
                                    $display("There is dependency on the third operation");
                                    $display("Will only load instructions 0 adn 1");
                                    instructionTemp[63:32] = instruction_mem[63:32];
                                    PCinTemp[63:32] = PCsIM+1;
                                    current_pc = current_pc + 2;
                                end
                                else if (dependency[3] == 1'b1)
                                begin
                                    $display("There is dependency on the fourth operation");
                                    $display("Will only load instructions 0, 1 and 2");
                                    instructionTemp[95:64] = instruction_mem[95:64];
                                    PCinTemp[95:64] = PCsIM+2;
                                    current_pc = current_pc + 3;
                                end
                                instruction_outPE <= instructionTemp;
                                PCinPE <= PCinTemp;
                            end
                            if (last_instruction)
                            begin
                                $display("The last instruction has been read");
                                end_execute <= 1;
                            end
                        end
                    end
                end
            end
        end
    end
endmodule

RISC-V_PE/ClusterControlTB.v
`include "ClusterControl.v"
`timescale 1ns / 1ps

module tb_cluster_controller;

    // Testbench signals
    reg clk;                        // Clock signal
    reg reset;                      // Reset signal
    reg [127:0] instruction_mem;    // Instructions from instruction memory (4 instructions)
    reg [127:0] PCoutPE;            // Program counter outputs from PEs
    reg [3:0] execution_complete;
    reg last_instruction;
    wire [31:0] PCsIM;             // Program counters sent to instruction memory
    wire [3:0] InstReadEn;          // Read enable signals for instruction memory
    wire [127:0] PCinPE;            // Program counters sent to PEs
    wire [127:0] instruction_outPE; // Instructions loaded into PEs

    // Instantiate the cluster_controller
    cluster_controller uut (
        .clk(clk),
        .reset(reset),
        .instruction_mem(instruction_mem),
        .PCsIM(PCsIM),
        .InstReadEn(InstReadEn),
        .PCinPE(PCinPE),
        .instruction_outPE(instruction_outPE),
        .PCoutPE(PCoutPE),
        .execution_complete(execution_complete),
        .last_instruction(last_instruction)
    );

    // Clock generation
    initial begin
        clk = 0;
        forever #5 clk = ~clk; // Clock period = 10 time units
    end

    // Testbench logic
    initial begin
        // Dump waveform for debugging
        $dumpfile("tb_cluster_controller.vcd");
        $dumpvars(0, tb_cluster_controller);

        // Monitor outputs
        $monitor("Time: %0dns | PCsIM: %h | InstReadEn: %b | PCinPE: %h | instruction_outPE: %h", 
                 $time, PCsIM, InstReadEn, PCinPE, instruction_outPE);


        // Initialize signals
        reset = 1;
        instruction_mem = 128'b0;

        #10 reset = 0; // Release reset

        #10; //Give time for PCsIM and InstReadEn to load

        // Test Case 1: Initial instruction fetch
        instruction_mem = {32'h2BB81A3, 32'hC5F0B3, 32'h40C580B3, 32'h235AB83}; // 4 RISC-V instructions
        #20; // Allow time for fetch
        execution_complete = 1;

        // Test Case 2: Dependency-free instructions
        instruction_mem = {32'b00000000101001001000010110110011, 32'b00000000011100110000010000110011, 32'b00000000010000010000001010110011, 32'b00000000000100000000000110110011}; // No dependencies
        #20; // Allow time for dependency check

        // Test Case 3: Instructions with dependencies
        instruction_mem = {32'h00b002b3, 32'h00c00333, 32'h00d004b3, 32'h00e005b3}; // RAW and WAW dependencies
        last_instruction = 1;
        #20; // Allow time for processing

        // Test Case 4: Reset the controller
        reset = 1;
        #10 reset = 0;

        // End simulation
        #50 $finish;
    end

endmodule

RISC-V_PE/tb_cluster_controller.vcd
$date
	Mon Apr 21 18:52:22 2025
$end
$version
	Icarus Verilog
$end
$timescale
	1ps
$end
$scope module tb_cluster_controller $end
$var wire 128 ! instruction_outPE [127:0] $end
$var wire 32 " PCsIM [31:0] $end
$var wire 128 # PCinPE [127:0] $end
$var wire 4 $ InstReadEn [3:0] $end
$var reg 128 % PCoutPE [127:0] $end
$var reg 1 & clk $end
$var reg 4 ' execution_complete [3:0] $end
$var reg 128 ( instruction_mem [127:0] $end
$var reg 1 ) last_instruction $end
$var reg 1 * reset $end
$scope module uut $end
$var wire 128 + PCoutPE [127:0] $end
$var wire 1 & clk $end
$var wire 4 , execution_complete [3:0] $end
$var wire 128 - instruction_mem [127:0] $end
$var wire 1 ) last_instruction $end
$var wire 1 * reset $end
$var reg 4 . InstReadEn [3:0] $end
$var reg 128 / PCinPE [127:0] $end
$var reg 128 0 PCinTemp [127:0] $end
$var reg 32 1 PCsIM [31:0] $end
$var reg 32 2 current_pc [31:0] $end
$var reg 4 3 dependency [3:0] $end
$var reg 1 4 end_execute $end
$var reg 128 5 instructionTemp [127:0] $end
$var reg 128 6 instruction_outPE [127:0] $end
$var reg 1 7 program_start $end
$scope function register_extraction $end
$var reg 32 8 instruction [31:0] $end
$var reg 7 9 opcode [6:0] $end
$var reg 5 : rd [4:0] $end
$var reg 5 ; rs1 [4:0] $end
$var reg 5 < rs2 [4:0] $end
$upscope $end
$scope task dependency_check $end
$var reg 4 = dependency_flags [3:0] $end
$var reg 128 > instructions [127:0] $end
$var reg 5 ? rdop1 [4:0] $end
$var reg 5 @ rdop2 [4:0] $end
$var reg 5 A rdop3 [4:0] $end
$var reg 5 B rdop4 [4:0] $end
$var reg 15 C regs1 [14:0] $end
$var reg 15 D regs2 [14:0] $end
$var reg 15 E regs3 [14:0] $end
$var reg 15 F regs4 [14:0] $end
$var reg 5 G rs1op1 [4:0] $end
$var reg 5 H rs1op2 [4:0] $end
$var reg 5 I rs1op3 [4:0] $end
$var reg 5 J rs1op4 [4:0] $end
$var reg 5 K rs2op1 [4:0] $end
$var reg 5 L rs2op2 [4:0] $end
$var reg 5 M rs2op3 [4:0] $end
$var reg 5 N rs2op4 [4:0] $end
$upscope $end
$upscope $end
$upscope $end
$enddefinitions $end
$comment Show the parameter values. $end
$dumpall
$end
#0
$dumpvars
bx N
bx M
bx L
bx K
bx J
bx I
bx H
bx G
bx F
bx E
bx D
bx C
bx B
bx A
bx @
bx ?
bx >
bx =
bx <
bx ;
bx :
bx 9
bx 8
17
b0 6
b0 5
04
b0 3
b0 2
b0 1
b0 0
b0 /
b0 .
b0 -
bx ,
bx +
1*
x)
b0 (
bx '
0&
bx %
b0 $
b0 #
b0 "
b0 !
$end
#5000
1&
#10000
0&
0*
#15000
b1111 $
b1111 .
1&
#20000
0&
b10101110111000000110100011000000001100010111110000101100110100000011000101100000001011001100000010001101011010101110000011 (
b10101110111000000110100011000000001100010111110000101100110100000011000101100000001011001100000010001101011010101110000011 -
#25000
07
b10001101011010101110000011 !
b10001101011010101110000011 6
b0 $
b0 .
b1 2
b0 5
b0 3
b1110 =
b1011 N
b10111 J
b0 B
b1100 M
b1011 I
b1 A
b1100 L
b1011 H
b1 @
b0 K
b1011 G
b10111 ?
b1011101011 F
b10101101100 E
b10101101100 D
b101110101100000 C
b1011 <
b10111 ;
b0 :
b100011 9
b10101110111000000110100011 8
b10101110111000000110100011000000001100010111110000101100110100000011000101100000001011001100000010001101011010101110000011 >
1&
#30000
0&
#35000
1&
#40000
0&
b101001001000010110110011000000000111001100000100001100110000000001000001000000101011001100000000000100000000000110110011 (
b101001001000010110110011000000000111001100000100001100110000000001000001000000101011001100000000000100000000000110110011 -
b1 '
b1 ,
#45000
b101 2
b100000000000000000000000000000000110000000000000000000000000000001000000000000000000000000000000001 #
b100000000000000000000000000000000110000000000000000000000000000001000000000000000000000000000000001 /
b101001001000010110110011000000000111001100000100001100110000000001000001000000101011001100000000000100000000000110110011 !
b101001001000010110110011000000000111001100000100001100110000000001000001000000101011001100000000000100000000000110110011 6
b0 $
b0 .
b0 =
b1010 N
b1001 J
b1011 B
b111 M
b110 I
b1000 A
b100 L
b10 H
b101 @
b1 K
b0 G
b11 ?
b10110100101010 F
b10000011000111 E
b1010001000100 D
b110000000001 C
b1011 :
b1010 <
b1001 ;
b110011 9
b101001001000010110110011 8
b101001001000010110110011000000000111001100000100001100110000000001000001000000101011001100000000000100000000000110110011 >
b1 "
b1 1
1&
#50000
0&
#55000
b1001 2
b1000000000000000000000000000000001110000000000000000000000000000011000000000000000000000000000000101 #
b1000000000000000000000000000000001110000000000000000000000000000011000000000000000000000000000000101 /
b0 $
b0 .
b1010 <
b1001 ;
b1011 :
b101001001000010110110011 8
b101 "
b101 1
1&
#60000
0&
1)
b101100000000001010110011000000001100000000000011001100110000000011010000000001001011001100000000111000000000010110110011 (
b101100000000001010110011000000001100000000000011001100110000000011010000000001001011001100000000111000000000010110110011 -
#65000
14
b1001 #
b1001 /
b111000000000010110110011 !
b111000000000010110110011 6
b0 $
b0 .
b1010 2
b1001 0
b0 5
b0 3
b1110 =
b1011 N
b0 J
b101 B
b1100 M
b0 I
b110 A
b1101 L
b0 H
b1001 @
b1110 K
b1011 ?
b1010000001011 F
b1100000001100 E
b10010000001101 D
b10110000001110 C
b1011 <
b0 ;
b101 :
b101100000000001010110011 8
b101100000000001010110011000000001100000000000011001100110000000011010000000001001011001100000000111000000000010110110011 >
b1001 "
b1001 1
1&
#70000
0&
#75000
1&
#80000
04
b0 0
17
b0 !
b0 6
b0 "
b0 1
b0 #
b0 /
b0 2
0&
1*
#85000
1&
#90000
0&
0*
#95000
07
b111000000000010110110011 !
b111000000000010110110011 6
b0 $
b0 .
b1 2
b0 5
b0 3
b1110 =
b1011 <
b101 :
b101100000000001010110011 8
1&
#100000
0&
#105000
14
b1 #
b1 /
b0 $
b0 .
b10 2
b1 0
b0 5
b0 3
b1110 =
b1011 <
b101 :
b101100000000001010110011 8
b1 "
b1 1
1&
