RISC-V_PE/ProcessingElement/reg.v
//Modelo del registro de 32 bits para registro de instrucciones y registros de entrada

module Register (
    input             clock,
    input             r_enable,
    input      [31:0] data_in,
    input             reset, // Add reset signal
    output reg [31:0] data_out
);
    

    always @(posedge clock or posedge reset) begin
        if (reset) begin
            data_out <= 32'b0; // Reset the output to 0
        end else if (r_enable) begin
            data_out <= data_in; // Load data on enable
        end
    end

endmodule

RISC-V_PE/ProcessingElement/RegTB.v
// Test bench for the register module

`include "reg.v"
`timescale 1ns / 1ps

module tb_Register;

    // Parameters
    reg clock;
    reg r_enable;
    reg reset;
    reg [31:0] data_in;
    wire [31:0] data_out;

    initial $dumpfile("registertestbench.vcd");
    initial $dumpvars(0, tb_Register);

    // Instantiate the Register module
    Register uut (
        .clock(clock),
        .r_enable(r_enable),
        .reset(reset),
        .data_in(data_in),
        .data_out(data_out)
    );

    // Clock generation
    initial begin
        clock = 0;
        forever #5 clock = ~clock; // Toggle clock every 5 time units
    end

    // Test procedure
    initial begin
        // Monitor outputs
        $monitor("Time: %0dns | Reset: %b | r_enable: %b | data_in: %h | data_out: %h", 
                 $time, reset, r_enable, data_in, data_out);

        // Initialize signals
        reset = 1; // Assert reset
        r_enable = 0; 
        data_in = 32'h00000030; 
        #10;

        reset = 0; // Deassert reset
        #10;

        // Test case 1: Enable register and load data
        r_enable = 1; 
        data_in = 32'hA5A5A5A5; 
        #10;

        // Check output after loading data
        r_enable = 0; // Disable register loading
        #10;

        // Test case 2: Load new data while enabled
        r_enable = 1; 
        data_in = 32'h5A5A5A5A; 
        #10;

        // Check output after loading new data
        r_enable = 0; // Disable register loading
        #10;

        // Test case 3: Assert reset again
        reset = 1; 
        #10;

        // Check output after reset (should be zero)
        reset = 0; 
        #10;

        // Final state check with no enable and some input data
        r_enable = 0; 
        data_in = 32'h12345678; 
        #10;

         $finish;
    end

endmodule

RISC-V_PE/ProcessingElement/registertestbench.vcd
$date
	Tue Mar 11 15:22:41 2025
$end
$version
	Icarus Verilog
$end
$timescale
	1ps
$end
$scope module tb_Register $end
$var wire 32 ! data_out [31:0] $end
$var reg 1 " clock $end
$var reg 32 # data_in [31:0] $end
$var reg 1 $ r_enable $end
$var reg 1 % reset $end
$scope module uut $end
$var wire 1 " clock $end
$var wire 32 & data_in [31:0] $end
$var wire 1 $ r_enable $end
$var wire 1 % reset $end
$var reg 32 ' data_out [31:0] $end
$upscope $end
$upscope $end
$enddefinitions $end
$comment Show the parameter values. $end
$dumpall
$end
#0
$dumpvars
b0 '
b110000 &
1%
0$
b110000 #
0"
b0 !
$end
#5000
1"
#10000
0"
0%
#15000
1"
#20000
0"
b10100101101001011010010110100101 #
b10100101101001011010010110100101 &
1$
#25000
b10100101101001011010010110100101 !
b10100101101001011010010110100101 '
1"
#30000
0"
0$
#35000
1"
#40000
0"
b1011010010110100101101001011010 #
b1011010010110100101101001011010 &
1$
#45000
b1011010010110100101101001011010 !
b1011010010110100101101001011010 '
1"
#50000
0"
0$
#55000
1"
#60000
b0 !
b0 '
0"
1%
#65000
1"
#70000
0"
0%
#75000
1"
#80000
0"
b10010001101000101011001111000 #
b10010001101000101011001111000 &
