RISC-V_PE/CGRA/ClusterArbiter.v
module cluster_mem_arbiter #(parameter NUM_CLUSTERS = 4)(
    input        clk,
    input        reset,
    input  [NUM_CLUSTERS-1:0] req_read,       // Read Request signals from the Clusters
    input  [NUM_CLUSTERS-1:0] req_write,       // Write Request signals from the Clusters
    input  [NUM_CLUSTERS-1:0] working,  // Signal indicating access to bus is being used
    output reg [NUM_CLUSTERS-1:0] grant_read,  // Grant signals to the Clusters to read
    output reg [NUM_CLUSTERS-1:0] grant_write  // Grant signals to the Clusters to write
);
    reg [1:0] current;      // Points to current priority slot
    reg [1:0] bus_owner;
    reg       bus_locked;
    reg [NUM_CLUSTERS-1:0] grant_pending_read;
    reg [NUM_CLUSTERS-1:0] grant_pending_write;
    reg release_wait;
    reg last_granted_type; // 0 = read, 1 = write
    

    always @(posedge clk or posedge reset) begin
    if (reset) begin
        grant_read      <= 4'b0000;
        grant_write      <= 4'b0000;
        grant_pending_read <= 4'b0000;
        grant_pending_write <= 4'b0000;
        current    <= 2'b00;
        bus_owner  <= 2'b00;
        bus_locked <= 1'b0;
        release_wait <= 1'b0;
        last_granted_type <= 1'b0;
    end else begin
        if (req_read != 0) $display("GlobalArbiter: Request status to read is: %b", req_read);
        if (req_write != 0) $display("GlobalArbiter: Request status to write is: %b", req_write);
        $display("Current use of bus is %d for current %b", working, current);

        // Default: no grant if no request
        grant_read <= 4'b0000;
        grant_write <= 4'b0000;

        if (!bus_locked) begin
            // Try to grant access based on rotating priority
            case (current)
                2'b00: 
                begin
                    if (req_read[0]) begin grant_pending_read <= 4'b0001; end
                    else if (req_read[1]) begin grant_pending_read <= 4'b0010; end
                    else if (req_read[2]) begin grant_pending_read <= 4'b0100; end
                    else if (req_read[3]) begin grant_pending_read <= 4'b1000; end
                    if (req_write[0]) begin grant_pending_write <= 4'b0001; end
                    else if (req_write[1]) begin grant_pending_write <= 4'b0010; end
                    else if (req_write[2]) begin grant_pending_write <= 4'b0100; end
                    else if (req_write[3]) begin grant_pending_write <= 4'b1000; end
                end
                2'b01: 
                begin
                    if (req_read[1]) begin grant_pending_read <= 4'b0010; end
                    else if (req_read[2]) begin grant_pending_read <= 4'b0100; end
                    else if (req_read[3]) begin grant_pending_read <= 4'b1000; end
                    else if (req_read[0]) begin grant_pending_read <= 4'b0001; end
                    if (req_write[1]) begin grant_pending_write <= 4'b0010; end
                    else if (req_write[2]) begin grant_pending_write <= 4'b0100; end
                    else if (req_write[3]) begin grant_pending_write <= 4'b1000; end
                    else if (req_write[0]) begin grant_pending_write <= 4'b0001; end
                end
                2'b10:
                begin
                    if (req_read[2]) begin grant_pending_read <= 4'b0100; end
                    else if (req_read[3]) begin grant_pending_read <= 4'b1000; end
                    else if (req_read[0]) begin grant_pending_read <= 4'b0001; end
                    else if (req_read[1]) begin grant_pending_read <= 4'b0010; end
                    if (req_write[2]) begin grant_pending_write <= 4'b0100; end
                    else if (req_write[3]) begin grant_pending_write <= 4'b1000; end
                    else if (req_write[0]) begin grant_pending_write <= 4'b0001; end
                    else if (req_write[1]) begin grant_pending_write <= 4'b0010; end
                end
                2'b11: 
                begin
                    if (req_read[3]) begin grant_pending_read <= 4'b1000; end
                    else if (req_read[0]) begin grant_pending_read <= 4'b0001; end
                    else if (req_read[1]) begin grant_pending_read <= 4'b0010; end
                    else if (req_read[2]) begin grant_pending_read <= 4'b0100; end
                    if (req_write[3]) begin grant_pending_write <= 4'b1000; end
                    else if (req_write[0]) begin grant_pending_write <= 4'b0001; end
                    else if (req_write[1]) begin grant_pending_write <= 4'b0010; end
                    else if (req_write[2]) begin grant_pending_write <= 4'b0100; end
                end
            endcase
        end else begin
            // Wait for Cluster to release the bus
            if (working[bus_owner] === 1'b0) begin
                $display("Bus owner %d is done working", bus_owner);
                if (release_wait) begin
                    $display("Bus is being released");
                    bus_locked <= 0;
                    release_wait <= 0;
                    grant_read      <= 4'b0000;
                    grant_write      <= 4'b0000;
                end else begin
                    release_wait <= 1;
                end
            end else begin
                release_wait <= 0; // Cluster is still working
            end
        end

        // Apply pending grant after Cluster has time to assert working
        if ((grant_pending_read != 0 || grant_pending_write != 0) && !bus_locked) begin
            $display("Grant pending are: read %b and write %b", grant_pending_read, grant_pending_write);

            if (last_granted_type == 0 && grant_pending_write != 0) begin
                grant_write <= grant_pending_write;
                bus_owner <= (grant_pending_write[3] ? 3 :
                        grant_pending_write[2] ? 2 :
                        grant_pending_write[1] ? 1 : 0);
                last_granted_type <= 1;
            end else if (last_granted_type == 1 && grant_pending_read != 0) begin
                grant_read <= grant_pending_read;
                bus_owner <= (grant_pending_read[3] ? 3 :
                        grant_pending_read[2] ? 2 :
                        grant_pending_read[1] ? 1 : 0);
                last_granted_type <= 0;
            end else if (grant_pending_read != 0) begin
                grant_read <= grant_pending_read;
                bus_owner <= (grant_pending_read[3] ? 3 :
                        grant_pending_read[2] ? 2 :
                        grant_pending_read[1] ? 1 : 0);
                last_granted_type <= 0;
            end else if (grant_pending_write != 0) begin
                grant_write <= grant_pending_write;
                bus_owner <= (grant_pending_write[3] ? 3 :
                        grant_pending_write[2] ? 2 :
                        grant_pending_write[1] ? 1 : 0);
                last_granted_type <= 1;
            end

            bus_locked <= 1;
            grant_pending_read <= 0;
            grant_pending_write <= 0;
        end

        // Rotate priority every cycle
        current <= current + 1;
    end
end

endmodule

RISC-V_PE/CGRA/ClusterArbiterTB.v
`include "ClusterArbiter.v"

`timescale 1ns / 1ps

module tb_cluster_mem_arbiter;

    parameter NUM_CLUSTERS = 4;

    reg clk;
    reg reset;
    reg [NUM_CLUSTERS-1:0] req_read;
    reg [NUM_CLUSTERS-1:0] req_write;
    reg [NUM_CLUSTERS-1:0] working;

    wire [NUM_CLUSTERS-1:0] grant_read;
    wire [NUM_CLUSTERS-1:0] grant_write;

    cluster_mem_arbiter #(.NUM_CLUSTERS(NUM_CLUSTERS)) dut (
        .clk(clk),
        .reset(reset),
        .req_read(req_read),
        .req_write(req_write),
        .working(working),
        .grant_read(grant_read),
        .grant_write(grant_write)
    );

    // Clock generation
    always #5 clk = ~clk;

    initial begin
        $dumpfile("arbiter_test.vcd");
        $dumpvars(0, tb_cluster_mem_arbiter);

        clk = 0;
        reset = 1;
        req_read = 0;
        req_write = 0;
        working = 0;

        #10;
        reset = 0;

        // === Cycle 1: Cluster 0 requests read ===
        req_read = 4'b0001;
        #20;
        $display("Cycle 1 at %t: grant_read = %b, grant_write = %b", $time, grant_read, grant_write);
        working = 4'b0001;
        #10;

        // === Cycle 2: Cluster 1 requests write ===
        req_read = 0;
        req_write = 4'b0010;
        #10;
        working = 4'b0000;
        #40;
        $display("Cycle 2 at %t: grant_read = %b, grant_write = %b", $time, grant_read, grant_write);
        working = 4'b0010;
        #10;

        // === Cycle 3: Cluster 2 requests read, Cluster 3 requests write ===
        req_read = 4'b0100;
        req_write = 4'b1000;
        #10;
        working = 4'b0000;
        #40;
        $display("Cycle 3 at %t: grant_read = %b, grant_write = %b", $time, grant_read, grant_write);
        working = 4'b0100;
        #10;

        // === Release bus still write request ===
        working = 0;
        req_read = 4'b0000;
        #40;
        $display("Cycle %t: grant_read = %b, grant_write = %b", $time, grant_read, grant_write);
        working = 4'b1000;
        #10;
        working = 0;

        // === Cycle 5: All clusters idle ===
        req_read = 0;
        req_write = 0;
        #40;
        $display("Cycle 5 at %t: grant_read = %b, grant_write = %b", $time, grant_read, grant_write);

        #20;
        $finish;
    end

endmodule

RISC-V_PE/CGRA/arbiter_test.vcd
$date
	Sat Nov  8 16:11:28 2025
$end
$version
	Icarus Verilog
$end
$timescale
	1ps
$end
$scope module tb_cluster_mem_arbiter $end
$var wire 4 ! grant_write [3:0] $end
$var wire 4 " grant_read [3:0] $end
$var parameter 32 # NUM_CLUSTERS $end
$var reg 1 $ clk $end
$var reg 4 % req_read [3:0] $end
$var reg 4 & req_write [3:0] $end
$var reg 1 ' reset $end
$var reg 4 ( working [3:0] $end
$scope module dut $end
$var wire 1 $ clk $end
$var wire 4 ) req_read [3:0] $end
$var wire 4 * req_write [3:0] $end
$var wire 1 ' reset $end
$var wire 4 + working [3:0] $end
$var parameter 32 , NUM_CLUSTERS $end
$var reg 1 - bus_locked $end
$var reg 2 . bus_owner [1:0] $end
$var reg 2 / current [1:0] $end
$var reg 4 0 grant_pending_read [3:0] $end
$var reg 4 1 grant_pending_write [3:0] $end
$var reg 4 2 grant_read [3:0] $end
$var reg 4 3 grant_write [3:0] $end
$var reg 1 4 last_granted_type $end
$var reg 1 5 release_wait $end
$upscope $end
$upscope $end
$enddefinitions $end
$comment Show the parameter values. $end
$dumpall
b100 ,
b100 #
$end
#0
$dumpvars
05
04
b0 3
b0 2
b0 1
b0 0
b0 /
b0 .
0-
b0 +
b0 *
b0 )
b0 (
1'
b0 &
b0 %
0$
b0 "
b0 !
$end
#5000
1$
#10000
0$
b1 %
b1 )
0'
#15000
b1 /
b1 0
1$
#20000
0$
#25000
b10 /
b0 0
1-
b1 "
b1 2
1$
#30000
0$
b1 (
b1 +
#35000
b11 /
b0 "
b0 2
1$
#40000
0$
b10 &
b10 *
b0 %
b0 )
#45000
b0 /
1$
#50000
0$
b0 (
b0 +
#55000
b1 /
15
1$
#60000
0$
#65000
b10 /
05
0-
1$
#70000
0$
#75000
b11 /
b10 1
1$
#80000
0$
#85000
b0 /
b0 1
1-
14
b1 .
b10 !
b10 3
1$
#90000
0$
b10 (
b10 +
#95000
b1 /
b0 !
b0 3
1$
#100000
0$
b1000 &
b1000 *
b100 %
b100 )
#105000
b10 /
1$
#110000
0$
b0 (
b0 +
#115000
b11 /
15
1$
#120000
0$
#125000
b0 /
05
0-
1$
#130000
0$
#135000
b1 /
b1000 1
b100 0
1$
#140000
0$
#145000
b10 /
b0 1
b0 0
1-
04
b10 .
b100 "
b100 2
1$
#150000
0$
b100 (
b100 +
#155000
b11 /
b0 "
b0 2
1$
#160000
0$
b0 %
b0 )
b0 (
b0 +
#165000
b0 /
15
1$
#170000
0$
#175000
b1 /
05
0-
1$
#180000
0$
#185000
b10 /
b1000 1
1$
#190000
0$
#195000
b11 /
b0 1
1-
14
b11 .
b1000 !
b1000 3
1$
#200000
0$
b1000 (
b1000 +
#205000
b0 /
b0 !
b0 3
1$
#210000
0$
b0 &
b0 *
b0 (
b0 +
#215000
b1 /
15
1$
#220000
0$
#225000
b10 /
05
0-
1$
#230000
0$
#235000
b11 /
1$
#240000
0$
#245000
b0 /
1$
#250000
0$
#255000
b1 /
1$
#260000
0$
#265000
b10 /
1$
