RISC-V_PE/CGRA/ClusterArbiter.v
module cluster_mem_arbiter #(parameter NUM_CLUSTERS = 4)(
    input        clk,
    input        reset,
    input  [NUM_CLUSTERS-1:0] req,       // Request signals from the Clusters
    input  [NUM_CLUSTERS-1:0] working,  // Signal indicating access to bus is being used
    output reg [NUM_CLUSTERS-1:0] grant  // Grant signals to the Clusters
);
    reg [1:0] current;      // Points to current priority slot
    reg [1:0] bus_owner;
    reg       bus_locked;
    reg [NUM_CLUSTERS-1:0] grant_pending;
    reg release_wait;
    

    always @(posedge clk or posedge reset) begin
    if (reset) begin
        grant      <= 4'b0000;
        grant_pending <= 4'b0000;
        current    <= 2'b00;
        bus_owner  <= 2'b00;
        bus_locked <= 1'b0;
        release_wait <= 1'b0;
    end else begin
        $display("Request status is: %b", req);
        $display("Current use of bus is %b for current %b", working, current);
        $display("Value of grant pending: %b and bus locked %b and bus owner %b", grant_pending, bus_locked, bus_owner);

        // Default: no grant if no request
        grant <= 4'b0000;

        if (!bus_locked) begin
            // Try to grant access based on rotating priority
            case (current)
                2'b00: if (req[0]) begin grant_pending <= 4'b0001; end
                       else if (req[1]) begin grant_pending <= 4'b0010; end
                       else if (req[2]) begin grant_pending <= 4'b0100; end
                       else if (req[3]) begin grant_pending <= 4'b1000; end
                2'b01: if (req[1]) begin grant_pending <= 4'b0010; end
                       else if (req[2]) begin grant_pending <= 4'b0100; end
                       else if (req[3]) begin grant_pending <= 4'b1000; end
                       else if (req[0]) begin grant_pending <= 4'b0001; end
                2'b10: if (req[2]) begin grant_pending <= 4'b0100; end
                       else if (req[3]) begin grant_pending <= 4'b1000; end
                       else if (req[0]) begin grant_pending <= 4'b0001; end
                       else if (req[1]) begin grant_pending <= 4'b0010; end
                2'b11: if (req[3]) begin grant_pending <= 4'b1000; end
                       else if (req[0]) begin grant_pending <= 4'b0001; end
                       else if (req[1]) begin grant_pending <= 4'b0010; end
                       else if (req[2]) begin grant_pending <= 4'b0100; end
            endcase
        end else begin
            // Wait for Cluster to release the bus
            if (working[bus_owner] === 1'b0) begin
                if (release_wait) begin
                    bus_locked <= 0;
                    release_wait <= 0;
                    grant      <= 4'b0000;
                end else begin
                    release_wait <= 1;
                end
            end else begin
                release_wait <= 0; // Cluster is still working
            end
        end

        // Apply pending grant after Cluster has time to assert working
        if (grant_pending != 0 && !bus_locked) begin
            grant      <= grant_pending;
            bus_owner  <= (grant_pending[3] ? 3 :
                          grant_pending[2] ? 2 :
                          grant_pending[1] ? 1 : 0);
            bus_locked <= 1;
            grant_pending <= 0;
        end

        // Rotate priority every cycle
        current <= current + 1;
    end
end

endmodule

RISC-V_PE/CGRA/ClusterArbiterTB.v
`include "ClusterArbiter.v"

`timescale 1ns / 1ps

module tb_cluster_arbiter;

    // Testbench signals
    reg clk;
    reg reset;
    reg [3:0] req;         // Request signals from Clusters
    reg [3:0] working;     // Signal to indicate bus is in use
    wire [3:0] grant;      // Grant signals from arbiter

    // Instantiate the arbiter module
    cluster_mem_arbiter uut (
        .clk(clk),
        .reset(reset),
        .req(req),
        .working(working),
        .grant(grant)
    );

    // Clock generation
    initial begin
        clk = 0;
        forever #5 clk = ~clk; // Clock Period = 10 time units
    end

    // Testbench logic
    initial begin
        // Dump waveform for debugging
        $dumpfile("tb_cluster_arbiter.vcd");
        $dumpvars(0, tb_cluster_arbiter);

        // Monitor outputs
        $monitor("Time: %0dns | grant: %b", 
                 $time, grant);


        // Initialize signals
        reset = 1;
        req = 4'b0000; // No requests initially
        #10 reset = 0; // Release reset

        $display("Test Case 1: Single Cluster requests (Cluster 0)");
        working = 4'b0000;
        #10 req = 4'b0001; // Cluster 0 requests access
        #10 //req = 4'b0000; // Clear request
        working = 4'b0001;

        #10 req = 4'b0000;

        #20 //give time to propagate
        working = 4'b0000;
        #10
        $display ("End of first case");

        $display("Test Case 2: Multiple requests (Cluster 1 and Cluster 3)");
        #10 req = 4'b1010; // Cluster 1 and Cluster 3 request access
        #10 working = 4'b1000;
        #10 req = 4'b0000;

        #20 working = 4'b0000;
        #10
        $display("End of second case");

        $display("Test Case 3: Sequential requests");
        #10 req = 4'b0100; // Cluster 2 requests access
        #10 req = 4'b0010; // Cluster 1 requests access
        working = 4'b0100;

        #20 working = 4'b0000;
        #10 working = 4'b0010;
        #10 req = 4'b0000;
        #20 working = 4'b0000;
        #10
        $display("End of third case");

        $display("Test Case 4: All Clusters request access");
        #10 req = 4'b1111; // All Clusters request access
        #10 working = 4'b0001; //Check to see which gets granted_index

        #20 working = 4'b0000;

        $display("Test Case 5: No requests");
        #10 req = 4'b0000; // No Clusters request access

        $display("Test Case 6: Persistent request (Cluster 0 keeps requesting access)");
        #10 req = 4'b0001; // Cluster 0 requests access again
        #50 req = 4'b0000; // Clear request

        $display("Test Case 7: Cluster requests access but previous is still using bus");
        working = 4'b0001;
        #10 req = 4'b0010; // Cluster 0 requests access again
        #50 req = 4'b0000; // Clear request

        // End simulation
        #10 $finish;
    end

endmodule

RISC-V_PE/CGRA/tb_cluster_arbiter.vcd
$date
	Mon Oct 27 18:27:20 2025
$end
$version
	Icarus Verilog
$end
$timescale
	1ps
$end
$scope module tb_cluster_arbiter $end
$var wire 4 ! grant [3:0] $end
$var reg 1 " clk $end
$var reg 4 # req [3:0] $end
$var reg 1 $ reset $end
$var reg 4 % working [3:0] $end
$scope module uut $end
$var wire 1 " clk $end
$var wire 4 & req [3:0] $end
$var wire 1 $ reset $end
$var wire 4 ' working [3:0] $end
$var parameter 32 ( NUM_CLUSTERS $end
$var reg 1 ) bus_locked $end
$var reg 2 * bus_owner [1:0] $end
$var reg 2 + current [1:0] $end
$var reg 4 , grant [3:0] $end
$var reg 4 - grant_pending [3:0] $end
$var reg 1 . release_wait $end
$upscope $end
$upscope $end
$enddefinitions $end
$comment Show the parameter values. $end
$dumpall
b100 (
$end
#0
$dumpvars
0.
b0 -
b0 ,
b0 +
b0 *
0)
bx '
b0 &
bx %
1$
b0 #
0"
b0 !
$end
#5000
1"
#10000
0"
b0 %
b0 '
0$
#15000
b1 +
1"
#20000
0"
b1 #
b1 &
#25000
b10 +
b1 -
1"
#30000
0"
b1 %
b1 '
#35000
b11 +
b0 -
1)
b1 !
b1 ,
1"
#40000
0"
b0 #
b0 &
#45000
b0 +
b0 !
b0 ,
1"
#50000
0"
#55000
b1 +
1"
#60000
0"
b0 %
b0 '
#65000
b10 +
1.
1"
#70000
0"
#75000
b11 +
0.
0)
1"
#80000
0"
b1010 #
b1010 &
#85000
b0 +
b1000 -
1"
#90000
0"
b1000 %
b1000 '
#95000
b1 +
1)
b11 *
b1000 !
b1000 ,
b0 -
1"
#100000
0"
b0 #
b0 &
#105000
b10 +
b0 !
b0 ,
1"
#110000
0"
#115000
b11 +
1"
#120000
0"
b0 %
b0 '
#125000
b0 +
1.
1"
#130000
0"
#135000
b1 +
0.
0)
1"
#140000
0"
b100 #
b100 &
#145000
b10 +
b100 -
1"
#150000
0"
b100 %
b100 '
b10 #
b10 &
#155000
b11 +
1)
b10 *
b100 !
b100 ,
b0 -
1"
#160000
0"
#165000
b0 +
b0 !
b0 ,
1"
#170000
0"
b0 %
b0 '
#175000
b1 +
1.
1"
#180000
0"
b10 %
b10 '
#185000
b10 +
0.
0)
1"
#190000
0"
b0 #
b0 &
#195000
b11 +
1"
#200000
0"
#205000
b0 +
1"
#210000
0"
b0 %
b0 '
#215000
b1 +
1"
#220000
0"
#225000
b10 +
1"
#230000
0"
b1111 #
b1111 &
#235000
b11 +
b100 -
1"
#240000
0"
b1 %
b1 '
#245000
b0 +
1)
b100 !
b100 ,
b0 -
1"
#250000
0"
#255000
b1 +
1.
b0 !
b0 ,
1"
#260000
0"
b0 %
b0 '
#265000
b10 +
0.
0)
1"
#270000
0"
b0 #
b0 &
#275000
b11 +
1"
#280000
0"
b1 #
b1 &
#285000
b0 +
b1 -
1"
#290000
0"
#295000
b1 +
b0 -
1)
b0 *
b1 !
b1 ,
1"
#300000
0"
#305000
b10 +
1.
b0 !
b0 ,
1"
#310000
0"
#315000
b11 +
0.
0)
1"
#320000
0"
#325000
b0 +
b1 -
1"
#330000
0"
b1 %
b1 '
b0 #
b0 &
#335000
b1 +
b0 -
1)
b1 !
b1 ,
1"
#340000
0"
b10 #
b10 &
#345000
b10 +
b0 !
b0 ,
1"
#350000
0"
#355000
b11 +
1"
#360000
0"
#365000
b0 +
1"
#370000
0"
#375000
b1 +
1"
#380000
0"
#385000
b10 +
1"
#390000
0"
b0 #
b0 &
#395000
b11 +
1"
